tests/__init__.py
tests/test.py
trumpy/__init__.py
trumpy/lib.py
trumpy-0.1.2.dist-info/LICENSE
trumpy-0.1.2.dist-info/METADATA
trumpy-0.1.2.dist-info/WHEEL
trumpy-0.1.2.dist-info/top_level.txt
trumpy-0.1.2.dist-info/RECORD
